<?xml version="1.0" encoding="windows-1251"?>
<packet>
  <zglv>
    <type>BaseRate</type>
    <version>1.66</version>
    <date>27.02.2023</date>
  </zglv>
  <zap>
    <TF_OKATO>01000</TF_OKATO>
    <IDUMP>1</IDUMP>
    <BZTSZ>23950.00</BZTSZ>
    <DATEBEG>01.01.2019</DATEBEG>
    <DATEEND>31.12.2019</DATEEND>
  </zap>
  <zap>
    <TF_OKATO>01000</TF_OKATO>
    <IDUMP>1</IDUMP>
    <BZTSZ>25885.00</BZTSZ>
    <DATEBEG>01.01.2020</DATEBEG>
    <DATEEND>31.12.2020</DATEEND>
  </zap>
  <zap>
    <TF_OKATO>01000</TF_OKATO>
    <IDUMP>1</IDUMP>
    <BZTSZ>26904.31</BZTSZ>
    <DATEBEG>01.01.2021</DATEBEG>
    <DATEEND/>
  </zap>
  <zap>
    <TF_OKATO>01000</TF_OKATO>
    <IDUMP>2</IDUMP>
    <BZTSZ>13275.00</BZTSZ>
    <DATEBEG>01.01.2019</DATEBEG>
    <DATEEND>31.12.2019</DATEEND>
  </zap>
  <zap>
    <TF_OKATO>01000</TF_OKATO>
    <IDUMP>2</IDUMP>
    <BZTSZ>14080.00</BZTSZ>
    <DATEBEG>01.01.2020</DATEBEG>
    <DATEEND>31.12.2020</DATEEND>
  </zap>
  <zap>
    <TF_OKATO>01000</TF_OKATO>
    <IDUMP>2</IDUMP>
    <BZTSZ>15237.92</BZTSZ>
    <DATEBEG>01.01.2021</DATEBEG>
    <DATEEND/>
  </zap>
  <zap>
    <TF_OKATO>05000</TF_OKATO>
    <IDUMP>1</IDUMP>
    <BZTSZ>18816.49</BZTSZ>
    <DATEBEG>01.01.2017</DATEBEG>
    <DATEEND>31.12.2017</DATEEND>
  </zap>
  <zap>
    <TF_OKATO>05000</TF_OKATO>
    <IDUMP>1</IDUMP>
    <BZTSZ>21317.42</BZTSZ>
    <DATEBEG>01.01.2018</DATEBEG>
    <DATEEND>31.12.2018</DATEEND>
  </zap>
  <zap>
    <TF_OKATO>05000</TF_OKATO>
    <IDUMP>1</IDUMP>
    <BZTSZ>20868.11</BZTSZ>
    <DATEBEG>01.01.2019</DATEBEG>
    <DATEEND>31.12.2019</DATEEND>
  </zap>
  <zap>
    <TF_OKATO>05000</TF_OKATO>
    <IDUMP>1</IDUMP>
    <BZTSZ>22598.52</BZTSZ>
    <DATEBEG>01.01.2020</DATEBEG>
    <DATEEND>31.12.2020</DATEEND>
  </zap>
  <zap>
    <TF_OKATO>05000</TF_OKATO>
    <IDUMP>1</IDUMP>
    <BZTSZ>23475.57</BZTSZ>
    <DATEBEG>01.01.2021</DATEBEG>
    <DATEEND>31.12.2021</DATEEND>
  </zap>
  <zap>
    <TF_OKATO>05000</TF_OKATO>
    <IDUMP>1</IDUMP>
    <BZTSZ>24277.10</BZTSZ>
    <DATEBEG>01.01.2022</DATEBEG>
    <DATEEND>31.12.2022</DATEEND>
  </zap>
  <zap>
    <TF_OKATO>05000</TF_OKATO>
    <IDUMP>1</IDUMP>
    <BZTSZ>25968.48</BZTSZ>
    <DATEBEG>01.01.2023</DATEBEG>
    <DATEEND/>
  </zap>
  <zap>
    <TF_OKATO>05000</TF_OKATO>
    <IDUMP>2</IDUMP>
    <BZTSZ>9638.12</BZTSZ>
    <DATEBEG>01.01.2017</DATEBEG>
    <DATEEND>31.12.2017</DATEEND>
  </zap>
  <zap>
    <TF_OKATO>05000</TF_OKATO>
    <IDUMP>2</IDUMP>
    <BZTSZ>11089.05</BZTSZ>
    <DATEBEG>01.01.2018</DATEBEG>
    <DATEEND>31.12.2018</DATEEND>
  </zap>
  <zap>
    <TF_OKATO>05000</TF_OKATO>
    <IDUMP>2</IDUMP>
    <BZTSZ>11567.79</BZTSZ>
    <DATEBEG>01.01.2019</DATEBEG>
    <DATEEND>31.12.2019</DATEEND>
  </zap>
  <zap>
    <TF_OKATO>05000</TF_OKATO>
    <IDUMP>2</IDUMP>
    <BZTSZ>12291.46</BZTSZ>
    <DATEBEG>01.01.2020</DATEBEG>
    <DATEEND>31.12.2020</DATEEND>
  </zap>
  <zap>
    <TF_OKATO>05000</TF_OKATO>
    <IDUMP>2</IDUMP>
    <BZTSZ>13308.72</BZTSZ>
    <DATEBEG>01.01.2021</DATEBEG>
    <DATEEND>31.12.2021</DATEEND>
  </zap>
  <zap>
    <TF_OKATO>05000</TF_OKATO>
    <IDUMP>2</IDUMP>
    <BZTSZ>13928.08</BZTSZ>
    <DATEBEG>01.01.2022</DATEBEG>
    <DATEEND>31.12.2022</DATEEND>
  </zap>
  <zap>
    <TF_OKATO>05000</TF_OKATO>
    <IDUMP>2</IDUMP>
    <BZTSZ>15029.12</BZTSZ>
    <DATEBEG>01.01.2023</DATEBEG>
    <DATEEND/>
  </zap>
  <zap>
    <TF_OKATO>08000</TF_OKATO>
    <IDUMP>1</IDUMP>
    <BZTSZ>22900.00</BZTSZ>
    <DATEBEG>01.01.2018</DATEBEG>
    <DATEEND>31.12.2018</DATEEND>
  </zap>
  <zap>
    <TF_OKATO>08000</TF_OKATO>
    <IDUMP>2</IDUMP>
    <BZTSZ>11480.00</BZTSZ>
    <DATEBEG>01.01.2018</DATEBEG>
    <DATEEND>31.12.2018</DATEEND>
  </zap>
  <zap>
    <TF_OKATO>08000</TF_OKATO>
    <IDUMP>3</IDUMP>
    <BZTSZ>0.00</BZTSZ>
    <DATEBEG>01.01.2018</DATEBEG>
    <DATEEND>31.12.2018</DATEEND>
  </zap>
  <zap>
    <TF_OKATO>08000</TF_OKATO>
    <IDUMP>4</IDUMP>
    <BZTSZ>0.00</BZTSZ>
    <DATEBEG>01.01.2018</DATEBEG>
    <DATEEND>31.12.2018</DATEEND>
  </zap>
  <zap>
    <TF_OKATO>20000</TF_OKATO>
    <IDUMP>1</IDUMP>
    <BZTSZ>26027.70</BZTSZ>
    <DATEBEG>01.01.2023</DATEBEG>
    <DATEEND>31.12.2023</DATEEND>
  </zap>
  <zap>
    <TF_OKATO>20000</TF_OKATO>
    <IDUMP>2</IDUMP>
    <BZTSZ>15063.54</BZTSZ>
    <DATEBEG>01.02.2023</DATEBEG>
    <DATEEND>31.12.2023</DATEEND>
  </zap>
  <zap>
    <TF_OKATO>28000</TF_OKATO>
    <IDUMP>1</IDUMP>
    <BZTSZ>17210.00</BZTSZ>
    <DATEBEG>01.01.2015</DATEBEG>
    <DATEEND>31.01.2015</DATEEND>
  </zap>
  <zap>
    <TF_OKATO>28000</TF_OKATO>
    <IDUMP>1</IDUMP>
    <BZTSZ>17210.00</BZTSZ>
    <DATEBEG>01.02.2015</DATEBEG>
    <DATEEND>31.05.2015</DATEEND>
  </zap>
  <zap>
    <TF_OKATO>30000</TF_OKATO>
    <IDUMP>1</IDUMP>
    <BZTSZ>76186.27</BZTSZ>
    <DATEBEG>01.01.2018</DATEBEG>
    <DATEEND>31.03.2018</DATEEND>
  </zap>
  <zap>
    <TF_OKATO>30000</TF_OKATO>
    <IDUMP>1</IDUMP>
    <BZTSZ>29336.26</BZTSZ>
    <DATEBEG>01.04.2018</DATEBEG>
    <DATEEND>31.12.2018</DATEEND>
  </zap>
  <zap>
    <TF_OKATO>30000</TF_OKATO>
    <IDUMP>1</IDUMP>
    <BZTSZ>28079.33</BZTSZ>
    <DATEBEG>01.01.2019</DATEBEG>
    <DATEEND>31.12.2019</DATEEND>
  </zap>
  <zap>
    <TF_OKATO>30000</TF_OKATO>
    <IDUMP>1</IDUMP>
    <BZTSZ>28850.94</BZTSZ>
    <DATEBEG>01.01.2020</DATEBEG>
    <DATEEND>31.12.2020</DATEEND>
  </zap>
  <zap>
    <TF_OKATO>30000</TF_OKATO>
    <IDUMP>1</IDUMP>
    <BZTSZ>24630.32</BZTSZ>
    <DATEBEG>01.01.2021</DATEBEG>
    <DATEEND>31.12.2021</DATEEND>
  </zap>
  <zap>
    <TF_OKATO>30000</TF_OKATO>
    <IDUMP>1</IDUMP>
    <BZTSZ>24238.27</BZTSZ>
    <DATEBEG>01.01.2022</DATEBEG>
    <DATEEND>31.12.2022</DATEEND>
  </zap>
  <zap>
    <TF_OKATO>30000</TF_OKATO>
    <IDUMP>1</IDUMP>
    <BZTSZ>33554.41</BZTSZ>
    <DATEBEG>01.01.2023</DATEBEG>
    <DATEEND/>
  </zap>
  <zap>
    <TF_OKATO>30000</TF_OKATO>
    <IDUMP>2</IDUMP>
    <BZTSZ>28435.13</BZTSZ>
    <DATEBEG>01.01.2018</DATEBEG>
    <DATEEND>31.03.2018</DATEEND>
  </zap>
  <zap>
    <TF_OKATO>30000</TF_OKATO>
    <IDUMP>2</IDUMP>
    <BZTSZ>10949.22</BZTSZ>
    <DATEBEG>01.04.2018</DATEBEG>
    <DATEEND>31.12.2018</DATEEND>
  </zap>
  <zap>
    <TF_OKATO>30000</TF_OKATO>
    <IDUMP>2</IDUMP>
    <BZTSZ>11981.07</BZTSZ>
    <DATEBEG>01.01.2019</DATEBEG>
    <DATEEND>31.12.2019</DATEEND>
  </zap>
  <zap>
    <TF_OKATO>30000</TF_OKATO>
    <IDUMP>2</IDUMP>
    <BZTSZ>11944.87</BZTSZ>
    <DATEBEG>01.01.2020</DATEBEG>
    <DATEEND>31.12.2020</DATEEND>
  </zap>
  <zap>
    <TF_OKATO>30000</TF_OKATO>
    <IDUMP>2</IDUMP>
    <BZTSZ>13559.84</BZTSZ>
    <DATEBEG>01.01.2021</DATEBEG>
    <DATEEND>31.12.2021</DATEEND>
  </zap>
  <zap>
    <TF_OKATO>30000</TF_OKATO>
    <IDUMP>2</IDUMP>
    <BZTSZ>13900.46</BZTSZ>
    <DATEBEG>01.01.2022</DATEBEG>
    <DATEEND>31.12.2022</DATEEND>
  </zap>
  <zap>
    <TF_OKATO>30000</TF_OKATO>
    <IDUMP>2</IDUMP>
    <BZTSZ>16107.27</BZTSZ>
    <DATEBEG>01.01.2023</DATEBEG>
    <DATEEND/>
  </zap>
  <zap>
    <TF_OKATO>32000</TF_OKATO>
    <IDUMP>1</IDUMP>
    <BZTSZ>27773.80</BZTSZ>
    <DATEBEG>01.01.2020</DATEBEG>
    <DATEEND>31.12.2020</DATEEND>
  </zap>
  <zap>
    <TF_OKATO>32000</TF_OKATO>
    <IDUMP>1</IDUMP>
    <BZTSZ>28419.24</BZTSZ>
    <DATEBEG>01.01.2021</DATEBEG>
    <DATEEND>31.01.2021</DATEEND>
  </zap>
  <zap>
    <TF_OKATO>32000</TF_OKATO>
    <IDUMP>1</IDUMP>
    <BZTSZ>28419.25</BZTSZ>
    <DATEBEG>01.02.2021</DATEBEG>
    <DATEEND>31.12.2021</DATEEND>
  </zap>
  <zap>
    <TF_OKATO>32000</TF_OKATO>
    <IDUMP>1</IDUMP>
    <BZTSZ>29411.46</BZTSZ>
    <DATEBEG>01.01.2022</DATEBEG>
    <DATEEND>31.12.2022</DATEEND>
  </zap>
  <zap>
    <TF_OKATO>32000</TF_OKATO>
    <IDUMP>1</IDUMP>
    <BZTSZ>31421.85</BZTSZ>
    <DATEBEG>01.01.2023</DATEBEG>
    <DATEEND/>
  </zap>
  <zap>
    <TF_OKATO>32000</TF_OKATO>
    <IDUMP>2</IDUMP>
    <BZTSZ>14849.89</BZTSZ>
    <DATEBEG>01.01.2020</DATEBEG>
    <DATEEND>31.12.2020</DATEEND>
  </zap>
  <zap>
    <TF_OKATO>32000</TF_OKATO>
    <IDUMP>2</IDUMP>
    <BZTSZ>16074.90</BZTSZ>
    <DATEBEG>01.01.2021</DATEBEG>
    <DATEEND>31.12.2021</DATEEND>
  </zap>
  <zap>
    <TF_OKATO>32000</TF_OKATO>
    <IDUMP>2</IDUMP>
    <BZTSZ>16837.92</BZTSZ>
    <DATEBEG>01.01.2022</DATEBEG>
    <DATEEND>31.12.2022</DATEEND>
  </zap>
  <zap>
    <TF_OKATO>32000</TF_OKATO>
    <IDUMP>2</IDUMP>
    <BZTSZ>18192.60</BZTSZ>
    <DATEBEG>01.01.2023</DATEBEG>
    <DATEEND/>
  </zap>
  <zap>
    <TF_OKATO>38000</TF_OKATO>
    <IDUMP>1</IDUMP>
    <BZTSZ>22563.91</BZTSZ>
    <DATEBEG>01.01.2020</DATEBEG>
    <DATEEND>31.12.2020</DATEEND>
  </zap>
  <zap>
    <TF_OKATO>38000</TF_OKATO>
    <IDUMP>1</IDUMP>
    <BZTSZ>23456.23</BZTSZ>
    <DATEBEG>01.01.2021</DATEBEG>
    <DATEEND>31.05.2021</DATEEND>
  </zap>
  <zap>
    <TF_OKATO>38000</TF_OKATO>
    <IDUMP>1</IDUMP>
    <BZTSZ>18764.98</BZTSZ>
    <DATEBEG>01.06.2021</DATEBEG>
    <DATEEND>31.12.2021</DATEEND>
  </zap>
  <zap>
    <TF_OKATO>38000</TF_OKATO>
    <IDUMP>1</IDUMP>
    <BZTSZ>19403.54</BZTSZ>
    <DATEBEG>01.01.2022</DATEBEG>
    <DATEEND>31.12.2022</DATEEND>
  </zap>
  <zap>
    <TF_OKATO>38000</TF_OKATO>
    <IDUMP>2</IDUMP>
    <BZTSZ>12272.64</BZTSZ>
    <DATEBEG>01.01.2020</DATEBEG>
    <DATEEND>31.12.2020</DATEEND>
  </zap>
  <zap>
    <TF_OKATO>38000</TF_OKATO>
    <IDUMP>2</IDUMP>
    <BZTSZ>13285.02</BZTSZ>
    <DATEBEG>01.01.2021</DATEBEG>
    <DATEEND>31.05.2021</DATEEND>
  </zap>
  <zap>
    <TF_OKATO>38000</TF_OKATO>
    <IDUMP>2</IDUMP>
    <BZTSZ>10628.02</BZTSZ>
    <DATEBEG>01.06.2021</DATEBEG>
    <DATEEND>31.12.2021</DATEEND>
  </zap>
  <zap>
    <TF_OKATO>38000</TF_OKATO>
    <IDUMP>2</IDUMP>
    <BZTSZ>11132.50</BZTSZ>
    <DATEBEG>01.01.2022</DATEBEG>
    <DATEEND>31.12.2022</DATEEND>
  </zap>
  <zap>
    <TF_OKATO>41000</TF_OKATO>
    <IDUMP>1</IDUMP>
    <BZTSZ>27256.05</BZTSZ>
    <DATEBEG>01.01.2019</DATEBEG>
    <DATEEND>31.12.2019</DATEEND>
  </zap>
  <zap>
    <TF_OKATO>41000</TF_OKATO>
    <IDUMP>1</IDUMP>
    <BZTSZ>27362.52</BZTSZ>
    <DATEBEG>01.01.2020</DATEBEG>
    <DATEEND>31.12.2020</DATEEND>
  </zap>
  <zap>
    <TF_OKATO>41000</TF_OKATO>
    <IDUMP>1</IDUMP>
    <BZTSZ>29664.00</BZTSZ>
    <DATEBEG>01.01.2021</DATEBEG>
    <DATEEND>31.12.2021</DATEEND>
  </zap>
  <zap>
    <TF_OKATO>41000</TF_OKATO>
    <IDUMP>2</IDUMP>
    <BZTSZ>13435.03</BZTSZ>
    <DATEBEG>01.01.2019</DATEBEG>
    <DATEEND>31.12.2019</DATEEND>
  </zap>
  <zap>
    <TF_OKATO>41000</TF_OKATO>
    <IDUMP>2</IDUMP>
    <BZTSZ>13663.91</BZTSZ>
    <DATEBEG>01.01.2020</DATEBEG>
    <DATEEND>31.12.2020</DATEEND>
  </zap>
  <zap>
    <TF_OKATO>41000</TF_OKATO>
    <IDUMP>2</IDUMP>
    <BZTSZ>14187.32</BZTSZ>
    <DATEBEG>01.01.2021</DATEBEG>
    <DATEEND>31.12.2021</DATEEND>
  </zap>
  <zap>
    <TF_OKATO>46000</TF_OKATO>
    <IDUMP>1</IDUMP>
    <BZTSZ>17700.00</BZTSZ>
    <DATEBEG>01.01.2018</DATEBEG>
    <DATEEND>31.08.2018</DATEEND>
  </zap>
  <zap>
    <TF_OKATO>46000</TF_OKATO>
    <IDUMP>1</IDUMP>
    <BZTSZ>19200.00</BZTSZ>
    <DATEBEG>01.09.2018</DATEBEG>
    <DATEEND>30.09.2018</DATEEND>
  </zap>
  <zap>
    <TF_OKATO>46000</TF_OKATO>
    <IDUMP>1</IDUMP>
    <BZTSZ>20500.00</BZTSZ>
    <DATEBEG>01.10.2018</DATEBEG>
    <DATEEND/>
  </zap>
  <zap>
    <TF_OKATO>46000</TF_OKATO>
    <IDUMP>2</IDUMP>
    <BZTSZ>7610.00</BZTSZ>
    <DATEBEG>01.01.2018</DATEBEG>
    <DATEEND>31.07.2018</DATEEND>
  </zap>
  <zap>
    <TF_OKATO>46000</TF_OKATO>
    <IDUMP>2</IDUMP>
    <BZTSZ>10200.00</BZTSZ>
    <DATEBEG>01.08.2018</DATEBEG>
    <DATEEND/>
  </zap>
  <zap>
    <TF_OKATO>54000</TF_OKATO>
    <IDUMP>1</IDUMP>
    <BZTSZ>24346.86</BZTSZ>
    <DATEBEG>01.01.2020</DATEBEG>
    <DATEEND/>
  </zap>
  <zap>
    <TF_OKATO>54000</TF_OKATO>
    <IDUMP>2</IDUMP>
    <BZTSZ>12273.04</BZTSZ>
    <DATEBEG>01.01.2020</DATEBEG>
    <DATEEND/>
  </zap>
  <zap>
    <TF_OKATO>58000</TF_OKATO>
    <IDUMP>1</IDUMP>
    <BZTSZ>24255.40</BZTSZ>
    <DATEBEG>01.01.2022</DATEBEG>
    <DATEEND/>
  </zap>
  <zap>
    <TF_OKATO>58000</TF_OKATO>
    <IDUMP>2</IDUMP>
    <BZTSZ>13915.70</BZTSZ>
    <DATEBEG>01.01.2022</DATEBEG>
    <DATEEND/>
  </zap>
  <zap>
    <TF_OKATO>61000</TF_OKATO>
    <IDUMP>1</IDUMP>
    <BZTSZ>23489.78</BZTSZ>
    <DATEBEG>01.01.2021</DATEBEG>
    <DATEEND>31.07.2021</DATEEND>
  </zap>
  <zap>
    <TF_OKATO>61000</TF_OKATO>
    <IDUMP>1</IDUMP>
    <BZTSZ>23519.32</BZTSZ>
    <DATEBEG>01.08.2021</DATEBEG>
    <DATEEND>31.12.2021</DATEEND>
  </zap>
  <zap>
    <TF_OKATO>61000</TF_OKATO>
    <IDUMP>1</IDUMP>
    <BZTSZ>24312.62</BZTSZ>
    <DATEBEG>01.01.2022</DATEBEG>
    <DATEEND/>
  </zap>
  <zap>
    <TF_OKATO>61000</TF_OKATO>
    <IDUMP>2</IDUMP>
    <BZTSZ>13347.73</BZTSZ>
    <DATEBEG>01.01.2021</DATEBEG>
    <DATEEND>31.12.2021</DATEEND>
  </zap>
  <zap>
    <TF_OKATO>61000</TF_OKATO>
    <IDUMP>2</IDUMP>
    <BZTSZ>13949.01</BZTSZ>
    <DATEBEG>01.01.2022</DATEBEG>
    <DATEEND/>
  </zap>
  <zap>
    <TF_OKATO>64000</TF_OKATO>
    <IDUMP>1</IDUMP>
    <BZTSZ>55234.00</BZTSZ>
    <DATEBEG>01.01.2021</DATEBEG>
    <DATEEND/>
  </zap>
  <zap>
    <TF_OKATO>64000</TF_OKATO>
    <IDUMP>2</IDUMP>
    <BZTSZ>31119.00</BZTSZ>
    <DATEBEG>01.01.2021</DATEBEG>
    <DATEEND/>
  </zap>
  <zap>
    <TF_OKATO>79000</TF_OKATO>
    <IDUMP>1</IDUMP>
    <BZTSZ>20854.32</BZTSZ>
    <DATEBEG>01.06.2019</DATEBEG>
    <DATEEND/>
  </zap>
  <zap>
    <TF_OKATO>79000</TF_OKATO>
    <IDUMP>2</IDUMP>
    <BZTSZ>15280.58</BZTSZ>
    <DATEBEG>01.01.2019</DATEBEG>
    <DATEEND/>
  </zap>
  <zap>
    <TF_OKATO>80000</TF_OKATO>
    <IDUMP>1</IDUMP>
    <BZTSZ>17912.52</BZTSZ>
    <DATEBEG>01.01.2018</DATEBEG>
    <DATEEND>31.03.2018</DATEEND>
  </zap>
  <zap>
    <TF_OKATO>80000</TF_OKATO>
    <IDUMP>1</IDUMP>
    <BZTSZ>18808.15</BZTSZ>
    <DATEBEG>01.04.2018</DATEBEG>
    <DATEEND>31.08.2018</DATEEND>
  </zap>
  <zap>
    <TF_OKATO>80000</TF_OKATO>
    <IDUMP>1</IDUMP>
    <BZTSZ>21629.37</BZTSZ>
    <DATEBEG>01.09.2018</DATEBEG>
    <DATEEND>30.09.2018</DATEEND>
  </zap>
  <zap>
    <TF_OKATO>80000</TF_OKATO>
    <IDUMP>1</IDUMP>
    <BZTSZ>18808.15</BZTSZ>
    <DATEBEG>01.10.2018</DATEBEG>
    <DATEEND>31.12.2018</DATEEND>
  </zap>
  <zap>
    <TF_OKATO>80000</TF_OKATO>
    <IDUMP>1</IDUMP>
    <BZTSZ>23581.83</BZTSZ>
    <DATEBEG>01.01.2019</DATEBEG>
    <DATEEND>31.03.2019</DATEEND>
  </zap>
  <zap>
    <TF_OKATO>80000</TF_OKATO>
    <IDUMP>1</IDUMP>
    <BZTSZ>23220.49</BZTSZ>
    <DATEBEG>01.04.2019</DATEBEG>
    <DATEEND>31.12.2019</DATEEND>
  </zap>
  <zap>
    <TF_OKATO>80000</TF_OKATO>
    <IDUMP>1</IDUMP>
    <BZTSZ>22643.46</BZTSZ>
    <DATEBEG>01.01.2020</DATEBEG>
    <DATEEND>31.12.2020</DATEEND>
  </zap>
  <zap>
    <TF_OKATO>80000</TF_OKATO>
    <IDUMP>1</IDUMP>
    <BZTSZ>23534.28</BZTSZ>
    <DATEBEG>01.01.2021</DATEBEG>
    <DATEEND>31.12.2021</DATEEND>
  </zap>
  <zap>
    <TF_OKATO>80000</TF_OKATO>
    <IDUMP>1</IDUMP>
    <BZTSZ>24332.69</BZTSZ>
    <DATEBEG>01.01.2022</DATEBEG>
    <DATEEND>30.09.2022</DATEEND>
  </zap>
  <zap>
    <TF_OKATO>80000</TF_OKATO>
    <IDUMP>1</IDUMP>
    <BZTSZ>27982.59</BZTSZ>
    <DATEBEG>01.10.2022</DATEBEG>
    <DATEEND>31.12.2022</DATEEND>
  </zap>
  <zap>
    <TF_OKATO>80000</TF_OKATO>
    <IDUMP>1</IDUMP>
    <BZTSZ>26025.71</BZTSZ>
    <DATEBEG>01.01.2023</DATEBEG>
    <DATEEND/>
  </zap>
  <zap>
    <TF_OKATO>80000</TF_OKATO>
    <IDUMP>2</IDUMP>
    <BZTSZ>8047.67</BZTSZ>
    <DATEBEG>01.01.2018</DATEBEG>
    <DATEEND>30.06.2018</DATEEND>
  </zap>
  <zap>
    <TF_OKATO>80000</TF_OKATO>
    <IDUMP>2</IDUMP>
    <BZTSZ>8450.05</BZTSZ>
    <DATEBEG>01.07.2018</DATEBEG>
    <DATEEND>31.12.2018</DATEEND>
  </zap>
  <zap>
    <TF_OKATO>80000</TF_OKATO>
    <IDUMP>2</IDUMP>
    <BZTSZ>13072.09</BZTSZ>
    <DATEBEG>01.01.2019</DATEBEG>
    <DATEEND>31.12.2019</DATEEND>
  </zap>
  <zap>
    <TF_OKATO>80000</TF_OKATO>
    <IDUMP>2</IDUMP>
    <BZTSZ>12315.91</BZTSZ>
    <DATEBEG>01.01.2020</DATEBEG>
    <DATEEND>31.12.2020</DATEEND>
  </zap>
  <zap>
    <TF_OKATO>80000</TF_OKATO>
    <IDUMP>2</IDUMP>
    <BZTSZ>13329.23</BZTSZ>
    <DATEBEG>01.01.2021</DATEBEG>
    <DATEEND>31.12.2021</DATEEND>
  </zap>
  <zap>
    <TF_OKATO>80000</TF_OKATO>
    <IDUMP>2</IDUMP>
    <BZTSZ>13959.96</BZTSZ>
    <DATEBEG>01.01.2022</DATEBEG>
    <DATEEND>31.12.2022</DATEEND>
  </zap>
  <zap>
    <TF_OKATO>80000</TF_OKATO>
    <IDUMP>2</IDUMP>
    <BZTSZ>15062.22</BZTSZ>
    <DATEBEG>01.01.2023</DATEBEG>
    <DATEEND/>
  </zap>
  <zap>
    <TF_OKATO>84000</TF_OKATO>
    <IDUMP>1</IDUMP>
    <BZTSZ>30795.06</BZTSZ>
    <DATEBEG>01.01.2019</DATEBEG>
    <DATEEND>31.08.2019</DATEEND>
  </zap>
  <zap>
    <TF_OKATO>84000</TF_OKATO>
    <IDUMP>1</IDUMP>
    <BZTSZ>33874.57</BZTSZ>
    <DATEBEG>01.09.2019</DATEBEG>
    <DATEEND>30.11.2019</DATEEND>
  </zap>
  <zap>
    <TF_OKATO>84000</TF_OKATO>
    <IDUMP>1</IDUMP>
    <BZTSZ>27582.20</BZTSZ>
    <DATEBEG>01.12.2019</DATEBEG>
    <DATEEND>31.12.2019</DATEEND>
  </zap>
  <zap>
    <TF_OKATO>84000</TF_OKATO>
    <IDUMP>1</IDUMP>
    <BZTSZ>32501.87</BZTSZ>
    <DATEBEG>01.01.2020</DATEBEG>
    <DATEEND/>
  </zap>
  <zap>
    <TF_OKATO>84000</TF_OKATO>
    <IDUMP>2</IDUMP>
    <BZTSZ>11559.66</BZTSZ>
    <DATEBEG>01.01.2019</DATEBEG>
    <DATEEND>31.01.2019</DATEEND>
  </zap>
  <zap>
    <TF_OKATO>84000</TF_OKATO>
    <IDUMP>2</IDUMP>
    <BZTSZ>11635.09</BZTSZ>
    <DATEBEG>01.02.2019</DATEBEG>
    <DATEEND>31.08.2019</DATEEND>
  </zap>
  <zap>
    <TF_OKATO>84000</TF_OKATO>
    <IDUMP>2</IDUMP>
    <BZTSZ>20943.16</BZTSZ>
    <DATEBEG>01.09.2019</DATEBEG>
    <DATEEND>30.11.2019</DATEEND>
  </zap>
  <zap>
    <TF_OKATO>84000</TF_OKATO>
    <IDUMP>2</IDUMP>
    <BZTSZ>14766.10</BZTSZ>
    <DATEBEG>01.12.2019</DATEBEG>
    <DATEEND>31.12.2019</DATEEND>
  </zap>
  <zap>
    <TF_OKATO>84000</TF_OKATO>
    <IDUMP>2</IDUMP>
    <BZTSZ>13964.05</BZTSZ>
    <DATEBEG>01.01.2020</DATEBEG>
    <DATEEND/>
  </zap>
  <zap>
    <TF_OKATO>93000</TF_OKATO>
    <IDUMP>1</IDUMP>
    <BZTSZ>23456.23</BZTSZ>
    <DATEBEG>01.01.2021</DATEBEG>
    <DATEEND/>
  </zap>
  <zap>
    <TF_OKATO>93000</TF_OKATO>
    <IDUMP>2</IDUMP>
    <BZTSZ>13285.02</BZTSZ>
    <DATEBEG>01.01.2021</DATEBEG>
    <DATEEND/>
  </zap>
  <zap>
    <TF_OKATO>96000</TF_OKATO>
    <IDUMP>1</IDUMP>
    <BZTSZ>22233.10</BZTSZ>
    <DATEBEG>01.01.2015</DATEBEG>
    <DATEEND>31.12.2015</DATEEND>
  </zap>
  <zap>
    <TF_OKATO>96000</TF_OKATO>
    <IDUMP>1</IDUMP>
    <BZTSZ>22815.30</BZTSZ>
    <DATEBEG>01.01.2016</DATEBEG>
    <DATEEND>31.12.2016</DATEEND>
  </zap>
  <zap>
    <TF_OKATO>96000</TF_OKATO>
    <IDUMP>1</IDUMP>
    <BZTSZ>21654.27</BZTSZ>
    <DATEBEG>01.01.2017</DATEBEG>
    <DATEEND>31.12.2017</DATEEND>
  </zap>
  <zap>
    <TF_OKATO>96000</TF_OKATO>
    <IDUMP>1</IDUMP>
    <BZTSZ>24408.63</BZTSZ>
    <DATEBEG>01.01.2018</DATEBEG>
    <DATEEND>31.12.2018</DATEEND>
  </zap>
  <zap>
    <TF_OKATO>96000</TF_OKATO>
    <IDUMP>1</IDUMP>
    <BZTSZ>25503.87</BZTSZ>
    <DATEBEG>01.01.2019</DATEBEG>
    <DATEEND>31.12.2019</DATEEND>
  </zap>
  <zap>
    <TF_OKATO>96000</TF_OKATO>
    <IDUMP>1</IDUMP>
    <BZTSZ>26948.45</BZTSZ>
    <DATEBEG>01.01.2020</DATEBEG>
    <DATEEND>31.12.2020</DATEEND>
  </zap>
  <zap>
    <TF_OKATO>96000</TF_OKATO>
    <IDUMP>1</IDUMP>
    <BZTSZ>28279.88</BZTSZ>
    <DATEBEG>01.01.2021</DATEBEG>
    <DATEEND/>
  </zap>
  <zap>
    <TF_OKATO>96000</TF_OKATO>
    <IDUMP>2</IDUMP>
    <BZTSZ>22233.10</BZTSZ>
    <DATEBEG>01.01.2015</DATEBEG>
    <DATEEND>31.12.2015</DATEEND>
  </zap>
  <zap>
    <TF_OKATO>96000</TF_OKATO>
    <IDUMP>2</IDUMP>
    <BZTSZ>11430.00</BZTSZ>
    <DATEBEG>01.01.2016</DATEBEG>
    <DATEEND>31.12.2016</DATEEND>
  </zap>
  <zap>
    <TF_OKATO>96000</TF_OKATO>
    <IDUMP>2</IDUMP>
    <BZTSZ>10835.58</BZTSZ>
    <DATEBEG>01.01.2017</DATEBEG>
    <DATEEND>31.12.2017</DATEEND>
  </zap>
  <zap>
    <TF_OKATO>96000</TF_OKATO>
    <IDUMP>2</IDUMP>
    <BZTSZ>12182.94</BZTSZ>
    <DATEBEG>01.01.2018</DATEBEG>
    <DATEEND>31.12.2018</DATEEND>
  </zap>
  <zap>
    <TF_OKATO>96000</TF_OKATO>
    <IDUMP>2</IDUMP>
    <BZTSZ>14177.28</BZTSZ>
    <DATEBEG>01.01.2019</DATEBEG>
    <DATEEND>31.12.2019</DATEEND>
  </zap>
  <zap>
    <TF_OKATO>96000</TF_OKATO>
    <IDUMP>2</IDUMP>
    <BZTSZ>15157.03</BZTSZ>
    <DATEBEG>01.01.2020</DATEBEG>
    <DATEEND>31.12.2020</DATEEND>
  </zap>
  <zap>
    <TF_OKATO>96000</TF_OKATO>
    <IDUMP>2</IDUMP>
    <BZTSZ>16665.42</BZTSZ>
    <DATEBEG>01.01.2021</DATEBEG>
    <DATEEND/>
  </zap>
  <zap>
    <TF_OKATO>97000</TF_OKATO>
    <IDUMP>1</IDUMP>
    <BZTSZ>21583.28</BZTSZ>
    <DATEBEG>01.09.2018</DATEBEG>
    <DATEEND/>
  </zap>
  <zap>
    <TF_OKATO>97000</TF_OKATO>
    <IDUMP>2</IDUMP>
    <BZTSZ>11409.56</BZTSZ>
    <DATEBEG>01.09.2018</DATEBEG>
    <DATEEND/>
  </zap>
</packet>